NAILNet_Snakemix66/__init__.py
NAILNet_Snakemix66/ai.py
nailnet_snakemix66-0.0.1.dist-info/METADATA
nailnet_snakemix66-0.0.1.dist-info/WHEEL
nailnet_snakemix66-0.0.1.dist-info/licenses/LICENSE
nailnet_snakemix66-0.0.1.dist-info/RECORD
